{"is_source_file": true, "format": "TypeScript/TSX", "description": "This file defines a React functional component named Arc, which renders an animated SVG ellipse (arc) with a gradient stroke that is configurable via props such as progress, rotation, colors, etc. It also includes helper functions for calculating the circumference of an arc.", "external_files": ["react", "remotion"], "external_methods": ["useState", "random", "useVideoConfig"], "published": ["Arc"], "classes": [], "methods": [{"name": "getCircumferenceOfArc", "description": "Calculates the circumference of an elliptical arc based on radius parameters rx and ry."}], "calls": ["useState", "random", "useVideoConfig"], "search-terms": ["Arc", "SVG ellipse", "Gradient stroke", "progress animation", "react functional component"], "state": 2, "file_id": 8, "knowledge_revision": 31, "git_revision": "f49491d48a74d8f79b7d97f4521b3aeec5bfde06", "ctags": [], "hash": "81c9128f01c7b242ea106b7d86496df5", "format-version": 4, "code-base-name": "recipe_app_video_frontend", "filename": "recipe_app_video_frontend/src/HelloWorld/Arc.tsx", "revision_history": [{"31": "f49491d48a74d8f79b7d97f4521b3aeec5bfde06"}]}